mezzy/__init__.py
mezzy/defaults.py
mezzy/templatetags/__init__.py
mezzy/templatetags/mezzy_calendar_tags.py
mezzy/templatetags/mezzy_tags.py
mezzy/utils/__init__.py
mezzy/utils/admin.py
mezzy/utils/forms.py
mezzy/utils/models.py
mezzy/utils/tests.py
mezzy/utils/views.py
mezzy-3.1.0.dist-info/LICENSE
mezzy-3.1.0.dist-info/METADATA
mezzy-3.1.0.dist-info/WHEEL
mezzy-3.1.0.dist-info/top_level.txt
mezzy-3.1.0.dist-info/RECORD
