Metadata-Version: 2.1
Name: mezzy
Version: 3.1.0
Summary: Utilities for Mezzanine CMS
Home-page: https://github.com/unplugstudio/mezzy
Author: Unplug Studio
Author-email: hello@unplug.studio
Maintainer: Unplug Studio
Maintainer-email: hello@unplug.studio
License: MIT
Project-URL: Source, https://github.com/unplugstudio/mezzy
Project-URL: Tracker, https://github.com/unplugstudio/mezzy/issues
Keywords: django,mezzanine,utilities,helpers
Platform: any
Classifier: Development Status :: 5 - Production/Stable
Classifier: Intended Audience :: Developers
Classifier: License :: OSI Approved :: MIT License
Classifier: Operating System :: OS Independent
Classifier: Topic :: Software Development :: Libraries
Classifier: Programming Language :: Python :: 3.6
Classifier: Programming Language :: Python :: 3.7
Classifier: Programming Language :: Python :: 3.8
Classifier: Programming Language :: Python :: 3.9
Requires-Python: >=3.6
License-File: LICENSE
Requires-Dist: mezzanine (>=4)
Requires-Dist: django (>=3.0)
Provides-Extra: testing
Requires-Dist: flake8 (<4,>=3) ; extra == 'testing'
Requires-Dist: pytest (<6,>=4.0.0) ; extra == 'testing'
